pyTinySoundFont/PySF2Synth.pyd
pyTinySoundFont/SF2.py
pyTinySoundFont/SF2Presets.py
pyTinySoundFont/SF2Synth.py
pyTinySoundFont/SF2SynthRT.py
pyTinySoundFont/__init__.py
pyTinySoundFont-0.0.1.dist-info/LICENSE
pyTinySoundFont-0.0.1.dist-info/METADATA
pyTinySoundFont-0.0.1.dist-info/WHEEL
pyTinySoundFont-0.0.1.dist-info/top_level.txt
pyTinySoundFont-0.0.1.dist-info/RECORD
