Metadata-Version: 2.1
Name: pyTinySoundFont
Version: 0.0.1
Summary: Python port of TinySoundFont
Home-page: https://github.com/fynv/pyTinySoundFont
Author: Fei Yang
Author-email: hyangfeih@gmail.com
License: UNKNOWN
Keywords: synthesizer soundfont sf2
Platform: UNKNOWN
License-File: LICENSE
